krome/.DS_Store
krome/__init__.py
krome/index_calc.py
krome/plotting.py
krome/spec_analysis.py
krome/.ipynb_checkpoints/__init__-checkpoint.py
krome/.ipynb_checkpoints/index_calc-checkpoint.py
krome/.ipynb_checkpoints/plotting-checkpoint.py
krome/.ipynb_checkpoints/spec_analysis-checkpoint.py
krome-1.3.1.dist-info/METADATA
krome-1.3.1.dist-info/WHEEL
krome-1.3.1.dist-info/licenses/LICENSE
krome-1.3.1.dist-info/RECORD
