Metadata-Version: 2.1
Name: krome
Version: 1.3.1
Summary: This is a test package upload for krome on TestPyPI
Project-URL: Homepage, https://github.com/MXK606/krome
Author-email: Mukul Kumar <mukulkumar531@gmail.com>
License-File: LICENSE
Classifier: License :: OSI Approved :: MIT License
Classifier: Operating System :: OS Independent
Classifier: Programming Language :: Python :: 3
Requires-Python: >=3.7
